hein_control/__init__.py
hein_control/automation.py
hein_control/db_tools.py
hein_control/scheduler.py
hein_control/timepoint.py
hein_control/version.py
hein_control/action/__init__.py
hein_control/action/basic.py
hein_control/action/configured.py
hein_control/action/logic.py
hein_control/action/operators.py
hein_control/mixin/__init__.py
hein_control/mixin/config.py
hein_control/mixin/reg.py
hein_control/mixin/serialization.py
hein_control/mixin/status.py
hein_control/sequencing/__init__.py
hein_control/sequencing/automation.py
hein_control/sequencing/execution.py
hein_control/states/__init__.py
hein_control/states/abc.py
hein_control/states/component.py
tests/__init__.py
tests/test_actions.py
tests/test_automation.py
tests/test_db_tools.py
tests/test_registry.py
tests/test_scheduler.py
tests/test_sequencing.py
tests/test_serialization.py
tests/test_states.py
tests/test_timepoints.py
hein_control-7.4.8.dist-info/METADATA
hein_control-7.4.8.dist-info/WHEEL
hein_control-7.4.8.dist-info/top_level.txt
hein_control-7.4.8.dist-info/RECORD
