Metadata-Version: 2.1
Name: hein-control
Version: 7.4.8
Summary: Code for automation and scheduling
Home-page: https://gitlab.com/heingroup/hein_control
Author: Lars Yunker // Hein Group
Author-email: 
License: MIT
Platform: UNKNOWN
